{
 "kitab": "talkhish-riyadl-ibtidaiyah-2",
 "judul": "Talkhish Riyadush Shalihin (Ibtidaiyah 2)",
 "bab": {
  "bab-131": {
   "nama": "131- باب فضل السلام والأمر بإفشائه",
   "urutan": 131,
   "segmen": {
    "1": {
     "arab": "وعن عبد الله بن عمرو بن العاص رضي الله عنهما: أنَّ رجلاً سأل رسول الله : أيُّ الإسْلاَمِ خَيْرٌ؟ قَالَ: ((تُطْعِمُ الطَّعَامَ، وَتَقْرَأُ السَّلاَمَ عَلَى مَنْ عَرَفْتَ وَمَنْ لَمْ تَعْرِفْ)) متفقٌ عَلَيْهِ.",
     "no": "1/1"
    },
    "2": {
     "arab": "وعن أَبي عُمَارة البراءِ بن عازِبٍ رضي الله عنهما، قَالَ: أمرنا رسول الله  بِسَبْعٍ: بِعِيَادَةِ المَرِيضِ، وَاتِّبَاعِ الجَنَائِزِ، وَتَشْمِيتِ العَاطِسِ، وَنَصْرِ الضَّعيفِ، وَعَوْنِ المَظْلُومِ، وَإفْشَاءِ السَّلاَمِ، وَإبْرَارِ المُقسِمِ. متفقٌ عَلَيْهِ، هَذَا لفظ إحدى روايات البخاري.",
     "no": "2/2"
    },
    "3": {
     "arab": "وعن أَبي هريرة ، قَالَ: قَالَ رسول الله : ((لاَ تَدْخُلُوا الجَنَّةَ حَتَّى تُؤمِنُوا، وَلاَ تُؤْمِنُوا حَتَّى تَحَابُّوا، أوَلاَ أدُلُّكُمْ عَلَى شَيْءٍ إِذَا فَعَلْتُمُوهُ تَحَابَبتُمْ ؟ أفْشُوا السَّلاَمَ بَيْنَكُمْ)) رواه مسلم.",
     "no": "3/3"
    },
    "4": {
     "arab": "وعن أَبي يوسف عبد الله بن سلام ، قَالَ: سَمِعْتُ رسول الله ، يقول: ((يَا أيُّهَا النَّاسُ، أفْشُوا السَّلاَمَ، وَأطْعِمُوا الطَّعَامَ، وَصِلُوا الأرْحَامَ، وَصَلُّوا والنَّاسُ نِيَامٌ، تَدْخُلُوا الجَنَّةَ بِسَلاَم)) رواه الترمذي، وقال: ((حديث حسن صحيح)).",
     "no": "4/4"
    }
   }
  },
  "bab-132": {
   "nama": "132- باب كيفية السلام",
   "urutan": 132,
   "segmen": {
    "1": {
     "arab": "عن عِمْرَان بن الحصين رضي الله عنهما، قَالَ: جَاءَ رَجُلٌ إِلَى النَّبيِّ ، فَقَالَ: السَّلاَمُ عَلَيْكُمْ، فَرَدَّ عَلَيْهِ ثُمَّ جَلَس، فَقَالَ النبيُّ : ((عَشْرٌ)) ثُمَّ جَاءَ آخَرُ، فَقَالَ: السَّلاَمُ عَلَيْكُمْ وَرَحْمَةُ اللهِ، فَرَدَّ عَلَيْهِ فَجَلَسَ، فَقَالَ: ((عِشْرُونَ)) ثُمَّ جَاءَ آخَرُ، فَقَالَ: السَّلاَمُ عَلَيْكُمْ وَرَحْمَةُ الله وَبَركَاتُهُ، فَرَدَّ عَلَيْهِ فَجَلَسَ، فَقَالَ: ((ثَلاثُونَ)) رواه أَبُو داود والترمذي، وقال: ((حديث حسن)).",
     "no": "1/5"
    },
    "2": {
     "arab": "وعن أَبي جُرَيٍّ الهُجَيْمِيِّ ، قَالَ: أتيت رسول الله ، فقلتُ: عَلَيْكَ السَّلامُ يَا رسول الله. قَالَ: ((لاَ تَقُلْ عَلَيْكَ السَّلامُ ؛ فإنَّ عَلَيْكَ السَّلاَمُ تَحِيَّةُ المَوتَى)) رواه أَبُو داود والترمذي، وقال: ((حديث حسن صحيح))، وَقَدْ سبق بِطُولِهِ.",
     "no": "2/6"
    }
   }
  },
  "bab-133": {
   "nama": "133- باب آداب السلام",
   "urutan": 133,
   "segmen": {
    "1": {
     "arab": "عن أَبي هريرة  : أنَّ رسول الله ، قَالَ: ((يُسَلِّمُ الرَّاكِبُ عَلَى المَاشِي، وَالمَاشِي عَلَى القَاعِدِ، وَالقَليلُ عَلَى الكَثِيرِ)) متفقٌ عَلَيْهِ. وفي رواية للبخاري: ((والصغيرُ عَلَى الكَبيرِ)).",
     "no": "1/7"
    },
    "2": {
     "arab": "وعن أَبي أُمَامَة صُدَيِّ بن عجلان الباهِلي ، قَالَ: قَالَ رسولُ الله : ((إنَّ أَوْلى النَّاسِ بِاللهِ مَنْ بَدَأهُمْ بِالسَّلامِ)) رواه أَبُو داود بإسنادٍ جيدٍ. ورواه الترمذي عن أَبي أُمَامَةَ ، قِيلَ: يَا رسول الله، الرَّجُلانِ يَلْتَقِيَانِ أَيُّهُمَا يَبْدَأُ بِالسَّلاَمِ ؟، قَالَ: ((أَوْلاَهُمَا بِاللهِ تَعَالَى)) قَالَ الترمذي: ((هَذَا حديث حسن)).",
     "no": "2/8"
    }
   }
  },
  "bab-134": {
   "nama": "134- باب استحباب إعادة السلام عَلَى من تكرر لقاؤه عَلَى قرب بأن دخل ثم خرج، ثُمَّ دخل في الحال، أَو حال بينهما شجرةٌ ونحوهما",
   "urutan": 134,
   "segmen": {
    "1": {
     "arab": "عن أَبي هريرة  في حديثِ المسِيءِ صلاته: أنّه جَاءَ فَصَلَّى، ثُمَّ جَاءَ إِلَى النَّبيِّ ، فَسَلَّمَ عَلَيْهِ، فَرَدَّ عَلَيْهِ السَّلاَمَ، فَقَالَ: ((ارْجِعْ فَصَلِّ فَإنَّكَ لَمْ تُصَلِّ)) فَرَجَعَ فَصَلَّى، ثُمَّ جَاءَ فَسَلَّمَ عَلَى النَّبيِّ ، حَتَّى فَعَلَ ذَلِكَ ثَلاثَ مَرَّاتٍ. متفقٌ عَلَيْهِ.",
     "no": "1/9"
    },
    "2": {
     "arab": "وعنه، عن رسول الله ، قَالَ: ((إِذَا لَقِيَ أَحَدُكُمْ أخَاهُ فَلْيُسَلِّمْ عَلَيْهِ، فَإنْ حَالَتْ بَيْنَهُمَا شَجَرَةٌ، أَوْ جِدَارٌ، أَوْ حَجَرٌ، ثُمَّ لَقِيَهُ، فَلْيُسَلِّمْ عَلَيْهِ)) رواه أَبُو داود.",
     "no": "2/10"
    }
   }
  },
  "bab-135": {
   "nama": "135- باب استحباب السلام إِذَا دخل بيته",
   "urutan": 135,
   "segmen": {
    "1": {
     "arab": "وعن أنسٍ ، قَالَ: قَالَ لي رسول الله : ((يَا بُنَيَّ، إِذَا دَخَلْتَ عَلَى أهْلِكَ، فَسَلِّمْ، يَكُنْ بَرَكَةً عَلَيْكَ، وعلى أهْلِ بَيْتِكَ)) رواه الترمذي، وقال: ((حديث حسن صحيح)).",
     "no": "1/11"
    }
   }
  },
  "bab-136": {
   "nama": "136- باب السلام عَلَى الصبيان",
   "urutan": 136,
   "segmen": {
    "1": {
     "arab": "عن أنس : أنَّهُ مَرَّ عَلَى صِبْيَانٍ، فَسَلَّمَ عَلَيْهِمْ، وقال: كَانَ رسول الله  يَفْعَلُهُ. متفقٌ عَلَيْهِ.",
     "no": "1/12"
    }
   }
  },
  "bab-137": {
   "nama": "137- باب سلام الرجل على زوجته والمرأة من محارمه وعلى أجنبية وأجنبيات لا يخاف الفتنة بهن وسلامهن بهذا الشرط",
   "urutan": 137,
   "segmen": {
    "1": {
     "arab": "عن سهل بن سعدٍ ، قال: كَانَتْ فِينَا امْرَأةٌ - وفي رواية: كَانَتْ لَنَا عَجُوزٌ - تَأخُذُ مِنْ أصُولِ السِّلْقِ فَتَطْرَحُهُ فِي القِدْرِ، وَتُكَرْكِرُ حَبَّاتٍ مِنْ شَعِيرٍ، فَإذَا صَلَّيْنَا الْجُمُعَةَ، وَانْصَرَفْنَا، نُسَلِّمُ عَلَيْهَا، فَتُقَدِّمُهُ إلَيْنَا. رواه البخاري. قَوْله: ((تُكَرْكِرُ)) أيْ: تَطْحَنُ.",
     "no": "1/13"
    },
    "2": {
     "arab": "وعن أُم هَانِىءٍ فاخِتَةَ بنتِ أَبي طالب رضي الله عنها، قالت: أتيت النبيَّ  يَوْمَ الفَتْحِ وَهُوَ يَغْتَسِلُ، وَفَاطِمَةُ تَسْتُرُهُ بِثَوْبٍ، فَسَلَّمْتُ... وَذَكَرَتِ الحديث. رواه مسلم.",
     "no": "2/14"
    },
    "3": {
     "arab": "وعن أسماءَ بنتِ يزيدَ رضي الله عنها، قالت: مَرّ عَلَيْنَا النّبيُّ  فِي نِسوَةٍ فَسَلَّمَ عَلَيْنَا. رواه أَبُو داود والترمذي، وقال: ((حديث حسن))، وهذا لفظ أَبي داود. ولفظ الترمذي: أنَّ رسول الله  مَرَّ في المَسْجِدِ يَوْماً، وَعُصْبَةٌ مِنَ النِّسَاءِ قُعُودٌ، فَأَلْوَى بِيَدِهِ بالتَّسْلِيمِ.",
     "no": "3/15"
    }
   }
  },
  "bab-138": {
   "nama": "138- باب تحريم ابتدائنا الكافرَ بالسلام وكيفيةِ الرد عليهم واستحبابِ السلام عَلَى أهل مجلسٍ فيهم مسلمون وكفار",
   "urutan": 138,
   "segmen": {
    "1": {
     "arab": "وعن أَبي هريرة : أنَّ رسول الله ، قَالَ: ((لاَ تَبْدَأُوا اليَهُودَ وَلاَ النَّصَارَى بالسَّلامِ، فَإِذَا لَقِيتُمْ أَحَدَهُمْ في طَرِيق فَاضطَرُّوهُ إِلَى أَضْيَقِهِ. رواه مسلم.",
     "no": "1/16"
    },
    "2": {
     "arab": "وعن أنسٍ ، قَالَ: قَالَ رسول الله : ((إِذَا سَلَّمَ عَلَيْكُمْ أهْلُ الكِتَابِ فَقُولُوا: وَعَلَيْكُمْ)) متفقٌ عَلَيْهِ.",
     "no": "2/17"
    },
    "3": {
     "arab": "وعن أُسَامَة : أنَّ النَّبيَّ  مَرَّ عَلَى مَجْلِسٍ فِيهِ أخْلاَطٌ مِنَ المُسْلِمِينَ وَالمُشْرِكينَ - عَبَدَة الأَوْثَانِ - واليَهُودِ فَسَلَّمَ عَلَيْهِم النبيُّ . متفقٌ عَلَيْهِ.",
     "no": "3/18"
    }
   }
  },
  "bab-139": {
   "nama": "139- باب استحباب السلام إِذَا قام من المجلس وفارق جلساءه أَوْ جليسه",
   "urutan": 139,
   "segmen": {
    "1": {
     "arab": "وعن أَبي هريرة ، قَالَ: قَالَ رسول الله : ((إِذَا انْتَهى أَحَدُكُمْ إِلَى المَجْلِسِ فَلْيُسَلِّمْ، فَإذَا أرَادَ أنْ يَقُومَ فَلْيُسَلِّمْ، فَلَيْسَتِ الأُولَى بِأحَقّ مِنَ الآخِرَةِ)) رواه أَبُو داود والترمذي، وقال: ((حديث حسن)).",
     "no": "1/19"
    }
   }
  },
  "bab-140": {
   "nama": "140- باب الاستئذان وآدابه",
   "urutan": 140,
   "segmen": {
    "1": {
     "arab": "عن أَبي موسى الأشعري ، قَالَ: قَالَ رسول الله : ((الاسْتِئْذَانُ ثَلاثٌ، فَإنْ أُذِنَ لَكَ وَإِلاَّ فَارْجِعْ)) متفقٌ عَلَيْهِ.",
     "no": "1/20"
    },
    "2": {
     "arab": "عن كِلْدَةَ بن الحَنْبل ، قَالَ: أتَيْتُ النبيَّ ، فَدَخَلْتُ عَلَيْهِ وَلَمْ أُسَلِّمْ، فَقَالَ النَّبيُّ : ((ارْجِعْ فَقُلْ: السَّلاَمُ عَلَيْكُمْ، أَأَدْخُل ؟)) رواه أَبُو داود والترمذي، وقال: ((حديث حسن)).",
     "no": "2/21"
    }
   }
  },
  "bab-141": {
   "nama": "141- باب بيان أنَّ السنة إِذَا قيل للمستأذن: من أنت؟ أن يقول: فلان، فيسمي نفسه بما يعرف به من اسم أَوْ كنية وكراهة قوله: (أنا) ونحوها",
   "urutan": 141,
   "segmen": {
    "1": {
     "arab": "وعن أنس  في حديثه المشهور في الإسراءِ، قَالَ: قَالَ رسول الله : ((ثُمَّ صَعَدَ بي جِبْريلُ إِلَى السَّمَاءِ الدُّنْيَا فَاسْتَفْتَحَ، فقِيلَ: مَنْ هذَا ؟ قَالَ: جِبْريلُ، قِيلَ: وَمَنْ مَعَكَ ؟ قَالَ: مُحَمَّدٌ، ثُمَّ صَعَدَ إِلَى السَّمَاءِ الثَّانِيَةِ فاسْتَفْتَحَ، قِيلَ: مَنْ هَذَا؟ قَالَ: جِبْريل، قِيلَ: وَمَنْ مَعَكَ ؟ قَالَ: مُحَمَّدٌ وَالثَّالِثَةِ وَالرَّابِعَةِ وَسَائِرِهنَّ وَيُقَالُ فِي بَابِ كُلِّ سَمَاءٍ: مَنْ هَذَا ؟ فَيَقُولُ: جِبْريلُ)) متفقٌ عَلَيْهِ.",
     "no": "1/22"
    },
    "2": {
     "arab": "وعن أَبي ذرٍّ ، قَالَ: خَرَجْتُ لَيْلَةً مِنَ اللَّيَالِي، فَإذَا رسول الله  يَمْشِي وَحْدَهُ، فَجَعَلْتُ أمْشِي فِي ظلِّ القمَرِ، فَالْتَفَتَ فَرَآنِي، فَقَالَ: ((مَنْ هَذَا ؟)) فقلتُ: أَبُو ذَرٍّ. متفقٌ عَلَيْهِ.",
     "no": "2/23"
    },
    "3": {
     "arab": "وعن جابر ، قَالَ: أتَيْتُ النبيَّ  فَدَقَقْتُ البَابَ، فَقَالَ: ((مَنْ هَذَا ؟)) فَقُلتُ: أَنَا، فَقَالَ: ((أنَا، أنَا!)) كَأنَّهُ كَرِهَهَا. متفقٌ عَلَيْهِ.",
     "no": "3/24"
    }
   }
  },
  "bab-142": {
   "nama": "142- باب استحباب تشميت العاطس إِذَا حمد الله تَعَالَى وكراهة تشميته إذا لَمْ يحمد الله تَعَالَى وبيان آداب التشميت والعطاس والتثاؤب",
   "urutan": 142,
   "segmen": {
    "1": {
     "arab": "عن أَبي هريرة : أنَّ النبيَّ ، قَالَ: ((إنَّ الله يُحِبُّ العُطَاسَ، وَيَكْرَهُ التَّثَاؤُبَ، فَإذَا عَطَسَ أَحَدُكُمْ وَحَمِدَ الله تَعَالَى كَانَ حَقّاً عَلَى كُلِّ مُسْلِمٍ سَمِعَهُ أنْ يَقُولَ لَهُ: يَرْحَمُكَ اللهُ، وَأَمَّا التَّثَاؤُبُ فَإنَّمَا هُوَ مِنَ الشَّيْطَانِ، فَإذَا تَثَاءبَ أحَدُكُمْ فَلْيَرُدَّهُ مَا اسْتَطَاعَ، فَإنَّ أحَدَكُمْ إِذَا تَثَاءبَ ضَحِكَ مِنْهُ الشَّيْطَانُ)) رواه البخاري.",
     "no": "1/25"
    },
    "2": {
     "arab": "وعنه، عن النبيِّ ، قَالَ: ((إِذَا عَطَسَ أحَدُكُمْ فَلْيَقُلْ: الحَمْدُ للهِ، وَلْيَقُلْ لَهُ أخُوهُ أَوْ صَاحِبُهُ: يَرْحَمُكَ الله. فإذَا قَالَ لَهُ: يَرْحَمُكَ اللهُ، فَليَقُلْ: يَهْدِيكُمُ اللهُ وَيُصْلِحُ بَالَكُمْ)) رواه البخاري.",
     "no": "2/26"
    },
    "3": {
     "arab": "وعن أَبي موسى ، قَالَ: كَانَ اليَهُودُ يَتَعَاطَسُونَ عِنْدَ رسول اللهِ  ،  يَرْجُونَ  أنْ يَقُولَ لَهُمْ: يَرْحَمُكُم الله، فَيَقُولُ: ((يَهْدِيكُم اللهُ وَيُصْلِحُ بَالَكُمْ)) رواه أَبُو داود والترمذي، وقال: ((حديث حسن صحيح)).",
     "no": "3/27"
    },
    "4": {
     "arab": "وعن أَبي سعيد الخدري ، قَالَ: قَالَ رسول الله : ((إِذَا تَثَاءبَ أحَدُكُمْ فَلْيُمْسِكْ بِيَدِهِ عَلَى فِيهِ؛ فَإنَّ الشَّيْطَانَ يَدْخُلُ فِيْهِ)) رواه مسلم.",
     "no": "4/28"
    }
   }
  },
  "bab-143": {
   "nama": "143- باب استحباب المصافحة عِنْدَ اللقاء وبشاشة الوجه وتقبيل يد الرجل الصالح وتقبيل ولده شفقة ومعانقة القادم من سفر وكراهية الانحناء",
   "urutan": 143,
   "segmen": {
    "1": {
     "arab": "عن أَبي الخطاب قتادة، قَالَ: قُلْتُ لأَنَسٍ: أكَانَتِ المُصَافَحَةُ في أصْحَابِ رسولِ الله  ؟ قَالَ: نَعَمْ. رواه البخاري",
     "no": "1/29"
    },
    "2": {
     "arab": "وعن البراءِ ، قَالَ: قَالَ رسولُ الله : ((مَا مِنْ مُسْلِمَينِ يَلْتَقِيَانِ فَيَتَصَافَحَانِ إِلاَّ غُفِرَ لَهُمَا قَبْلَ أنْ يَفْتَرِقَا)) رواه أَبُو داود.",
     "no": "2/30"
    },
    "3": {
     "arab": "وعن عائشة رضي الله عنها، قالت: قَدِمَ زَيْدُ بْنُ حَارِثَةَ المَدِينَةَ وَرسولُ الله  في بَيتِي، فَأتَاهُ فَقَرَعَ البَابَ، فَقَامَ إِلَيْهِ النبيُّ  يَجُرُّ ثَوْبَهُ، فَاعْتَنَقَهُ وَقَبَّلَهُ. رواه الترمذي، وقال: ((حديث حسن)).",
     "no": "3/31"
    },
    "4": {
     "arab": "وعن أَبي ذَرٍّ ، قَالَ: قَالَ لي رسول الله : ((لا تَحقِرَنَّ منَ الْمَعرُوف شَيْئاً، وَلَوْ أنْ تَلْقَى أخَاكَ بِوَجْهٍ طَلْقٍ. رواه مسلم.",
     "no": "4/32"
    },
    "5": {
     "arab": "وعن أَبي هريرة ، قَالَ: قَبَّلَ النبيُّ  الحَسَنَ بنَ عَلِيٍّ رضي الله عنهما، فَقَالَ الأقْرَعُ بن حَابِسٍ: إنَّ لِي عَشْرَةً مِنَ الْوَلَدِ مَا قَبَّلْتُ مِنْهُمْ أحَدَاً. فَقَالَ رسول الله : ((مَنْ لاَ يَرْحَمْ لاَ يُرْحَمْ !)) متفقٌ عَلَيْهِ.",
     "no": "5/33"
    }
   }
  },
  "bab-144": {
   "nama": "144- باب عيادة المريض",
   "urutan": 144,
   "segmen": {
    "1": {
     "arab": "وعن أَبي هريرة : أنَّ رسول الله ، قَالَ: ((حَقُّ المُسْلِمِ عَلَى المُسْلِمِ خَمْسٌ: رَدُّ السَّلاَمِ، وَعِيَادَةُ المَرِيضِ، وَاتِّبَاعُ الجَنَائِزِ، وَإجَابَةُ الدَّعْوَةِ، وَتَشْمِيتُ العَاطِسِ)) متفقٌ عَلَيْهِ.",
     "no": "1/34"
    },
    "2": {
     "arab": "وعن عليّ ، قَالَ: سَمِعْتُ رسولَ الله ، يَقُولُ: ((مَا مِنْ مُسْلِم يَعُودُ مُسْلِماً غُدْوة إِلاَّ صَلَّى عَلَيْهِ سَبْعُونَ ألْفَ مَلَكٍ حَتَّى يُمْسِي، وَإنْ عَادَهُ عَشِيَّةً إِلاَّ صَلَّى عَلَيْهِ سَبْعُونَ ألْفَ مَلَكٍ حَتَّى يُصْبحَ، وَكَانَ لَهُ خَرِيفٌ     في الْجَنَّةِ)) رواه الترمذي، وقال: ((حديث حسن)). ((الخَريفُ)): الثَّمرُ الْمَخْرُوفُ، أيْ: الْمُجْتَنَى.",
     "no": "2/35"
    },
    "3": {
     "arab": "وعن أنسٍ ، قَالَ: كَانَ غُلاَمٌ يَهُودِيٌّ يَخْدُمُ النَّبيَّ ، فَمَرِضَ، فَأتَاهُ النَّبيُّ  يَعُودُهُ، فَقَعَدَ عِنْدَ رَأسِهِ، فَقَالَ لَهُ: ((أسْلِمْ)) فَنَظَرَ إِلَى أبِيهِ وَهُوَ عِنْدَهُ ؟ فَقَالَ: أَطِعْ أَبَا القَاسِمِ، فَأسْلَمَ، فَخَرَجَ النَّبيُّ ، وَهُوَ يَقُولُ: ((الحَمْدُ للهِ الَّذِي أنْقَذَهُ منَ النَّارِ)) رواه البخاري.",
     "no": "3/36"
    }
   }
  },
  "bab-145": {
   "nama": "145- باب مَا يُدعى به للمريض",
   "urutan": 145,
   "segmen": {
    "1": {
     "arab": "عن عائشة رضي الله عنها: أنَّ النَّبيَّ ، كَانَ إِذَا اشْتَكى الإنْسَانُ الشَّيْءَ مِنْهُ، أَوْ كَانَتْ بِهِ قَرْحَةٌ أَوْ جُرْحٌ، قَالَ النَّبيُّ  بِأُصْبُعِهِ هكَذا -وَوَضَعَ سُفْيَانُ بْنُ عُيَيْنَة الرَّاوي سَبَّابَتَهُ بِالأَرْضِ ثُمَّ رَفَعَها- وقال: ((بِسمِ اللهِ، تُرْبَةُ أرْضِنَا، بِرِيقَةِ بَعْضِنَا، يُشْفَى بِهِ سَقِيمُنَا، بإذْنِ رَبِّنَا((2)))) متفقٌ عَلَيْهِ.",
     "no": "1/37"
    },
    "2": {
     "arab": "وعنها: أنَّ النَّبيَّ  كَانَ يَعُودُ بَعْضَ أهْلِهِ يَمْسَحُ بِيدِهِ اليُمْنَى، ويقولُ: ((اللَّهُمَّ رَبَّ النَّاسِ، أذْهِب البَأسَ، اشْفِ أنْتَ الشَّافِي لاَ شِفَاءَ إِلاَّ شِفاؤكَ، شِفَاءً لاَ يُغَادِرُ سَقماً)) متفقٌ عَلَيْهِ.",
     "no": "2/38"
    },
    "3": {
     "arab": "وعن أنسٍ  أنه قَالَ لِثابِتٍ رحمه اللهُ: ألاَ أرْقِيكَ بِرُقْيَةِ رسول الله  ؟ قَالَ: بَلَى، قَالَ: ((اللَّهُمَّ رَبَّ النَّاسِ، مُذْهِبَ البَأسِ، اشْفِ أنْتَ الشَّافِي، لاَ شَافِيَ إِلاَّ أنْتَ، شِفَاءً لاَ يُغَادِرُ سَقماً)) رواه البخاري.",
     "no": "3/39"
    },
    "4": {
     "arab": "وعن أَبي عبدِ الله عثمان بنِ أَبي العاصِ : أنّه شَكَا إِلَى رسول الله  وَجَعاً، يَجِدُهُ في جَسَدِهِ، فَقَالَ لَهُ رسول الله : ((ضَعْ يَدَكَ عَلَى الَّذِي يَألَم مِنْ جَسَدِكَ وَقُلْ: بسم اللهِ ثَلاثاً، وَقُلْ سَبْعَ مَرَّاتٍ: أعُوذُ بِعِزَّةِ الله وَقُدْرَتِهِ مِنْ شَرِّ مَا أجِدُ وَأُحَاذِرُ)) رواه مسلم.",
     "no": "4/40"
    },
    "5": {
     "arab": "وعن ابن عباسٍ رضي الله عنهما، عن النبيِّ ، قَالَ: ((مَنْ عَادَ مَرِيضاً لَمْ يَحْضُرْهُ أجَلُهُ، فقالَ عِنْدَهُ سَبْعَ مَرَّاتٍ: أسْأَلُ اللهَ العَظيمَ، رَبَّ العَرْشِ العَظيمِ، أنْ يَشْفِيَكَ، إِلاَّ عَافَاهُ اللهُ مِنْ ذَلِكَ المَرَضِ)) رواه أَبُو داود والترمذي، وقال: ((حديث حسن))، وقال الحاكم: ((حديث صحيح عَلَى شرط البخاري)).",
     "no": "5/41"
    },
    "6": {
     "arab": "وعن أَبي سعيد الخدري : أن جِبريلَ أتَى النَّبيَّ ، فَقَالَ: يَا مُحَمَّدُ، اشْتَكَيْتَ ؟ قَالَ: ((نَعَمْ)) قَالَ: بِسْمِ الله أرْقِيكَ، مِنْ كُلِّ شَيْءٍ يُؤْذِيكَ، مِنْ شَرِّ كُلِّ نَفْسٍ أَوْ عَيْنِ حَاسِدٍ، اللهُ يَشْفِيكَ، بِسمِ اللهِ أُرقِيكَ. رواه مسلم.",
     "no": "6/42"
    }
   }
  },
  "bab-146": {
   "nama": "146- باب استحباب سؤال أهل المريض عن حاله",
   "urutan": 146,
   "segmen": {
    "1": {
     "arab": "عن ابن عباسٍ رضي الله عنهما: أنَّ عليَّ بْنَ أَبي طالب ، خَرَجَ مِنْ عِنْدِ رسولِ الله ، في وَجَعِهِ الَّذِي تُوُفِّيَ فِيهِ، فقالَ النَّاسُ: يَا أَبَا الحَسَنِ، كَيْفَ أصْبَحَ رَسُولُ اللهِ  ؟ قَالَ: أصْبَحَ بِحَمْدِ اللهِ بَارئاً. رواه البخاري.",
     "no": "1/43"
    }
   }
  },
  "bab-147": {
   "nama": "147- باب مَا يقوله مَن أيس من حياته",
   "urutan": 147,
   "segmen": {
    "1": {
     "arab": "عن عائشة رضي الله عنها، قالت: سَمِعْتُ النبيَّ  وَهُوَ مُسْتَنِدٌ إلَيَّ، يَقُولُ: ((اللَّهُمَّ اغْفِرْ لِي وارْحَمْنِي، وأَلْحِقْنِي بالرَّفِيقِ الأَعْلَى)) متفقٌ عَلَيْهِ.",
     "no": "1/44"
    },
    "2": {
     "arab": "وعنها، قالت: رَأيتُ رسولَ الله  وَهُوَ بِالمَوْتِ، عِنْدَهُ قَدَحٌ فِيهِ مَاءٌ، وَهُوَ يُدْخِلُ يَدَهُ في القَدَحِ، ثُمَّ يَمْسَحُ وَجْهَهُ بالماءِ، ثُمَّ يَقُولُ: ((اللَّهُمَّ أعِنِّي عَلَى غَمَرَاتِ المَوْتِ أَوْ سَكَرَاتِ المَوْتِ)) رواه الترمذي.",
     "no": "2/45"
    }
   }
  },
  "bab-148": {
   "nama": "148- باب استحباب وصية أهل المريض ومن يخدمه بالإحسان إليه واحتماله والصبر عَلَى مَا يشق من أمره وكذا الوصية بمن قرب سبب موته بحد أَوْ قصاص ونحوهما",
   "urutan": 148,
   "segmen": {
    "1": {
     "arab": "عن عِمْران بن الحُصَيْنِ رضي الله عنهما: أنَّ أمْرَأَةً مِنْ جُهَيْنَةَ أتَت النَّبِيَّ  وَهِيَ حُبْلَى مِنَ الزِّنَا، فَقَالَتْ:   يَا رسول الله، أصَبْتُ حَدّاً فَأقِمْهُ عَلَيَّ، فَدَعَا رسولُ الله  وَلِيَّهَا، فَقَالَ: ((أحْسِنْ إِلَيْهَا، فَإذَا وَضَعَتْ فَأتِنِي بِهَا)) فَفَعَلَ، فَأمَرَ بِهَا النَّبِيُّ ، فَشُدَّتْ عَلَيْهَا ثِيَابُهَا، ثُمَّ أمَرَ بِهَا فَرُجِمَت، ثُمَّ صَلَّى عَلَيْهَا. رواه مسلم.",
     "no": "1/46"
    }
   }
  },
  "bab-149": {
   "nama": "149- باب جواز قول المريض: أنَا وجع، أَوْ شديد الوجع أَوْ مَوْعُوكٌ أَوْ وارأساه ونحو ذلك. وبيان أنَّه لا كراهة في ذلك إِذَا لَمْ يكن عَلَى سبيل التسخط وإظهار الجزع",
   "urutan": 149,
   "segmen": {
    "1": {
     "arab": "عن ابن مسعود ، قَالَ: دَخَلْتُ عَلَى النَّبيِّ  وَهُوَ يُوعَكُ، فَمَسسْتُهُ، فَقلتُ: إنَّكَ لَتُوعَكُ وَعَكاً شَديداً، فَقَالَ: ((أجَلْ، إنِّي أُوعَكُ كَمَا يُوعَكُ رَجُلانِ مِنْكُمْ)) متفقٌ عَلَيْهِ.",
     "no": "1/47"
    },
    "2": {
     "arab": "وعن سعدِ بن أَبي وقاصٍ ، قَالَ: جَاءني رسولُ الله   يَعُودُنِي مِنْ وَجَعٍ اشْتَدَّ بِي، فقلتُ: بَلَغَ بِي مَا تَرَى، وَأنَا ذُو مَالٍ، وَلاَ يَرِثُنِي إِلاَّ ابْنَتِي - وذَكر الحديث -. متفقٌ عَلَيْهِ.",
     "no": "2/48"
    },
    "3": {
     "arab": "وعن القاسم بن محمد، قَالَ: قالت عائشةُ رضي الله عنها: وَارَأسَاهُ ! فَقَالَ النَّبيُّ : ((بَلْ أنَا، وَارَأسَاهُ !))  - وذكر الحديث -. رواه البخاري.",
     "no": "3/49"
    }
   }
  },
  "bab-150": {
   "nama": "150- باب تلقين المحتضر: لا إله إِلاَّ اللهُ",
   "urutan": 150,
   "segmen": {
    "1": {
     "arab": "عن معاذ ، قَالَ: قَالَ رسول الله : ((مَنْ كَانَ آخِرَ كَلامِهِ لاَ إلهَ إِلاَّ اللهُ دَخَلَ الجَنَّةَ)) رواه أَبُو داود والحاكم، وقال: ((صحيح الإسناد)).",
     "no": "1/50"
    },
    "2": {
     "arab": "وعن أَبي سعيد الخدري ، قَالَ: قَالَ رسولُ الله : ((لَقِّنُوا مَوْتَاكُمْ لاَ إلهَ إِلاَّ اللهُ)) رواه مسلم.",
     "no": "2/51"
    }
   }
  },
  "bab-151": {
   "nama": "151- باب مَا يقوله بعد تغميض الميت",
   "urutan": 151,
   "segmen": {
    "1": {
     "arab": "عن أُم سلمة رضي الله عنها، قالت: دَخَلَ رسولُ الله  عَلَى أَبي سَلَمة وَقَدْ شَقَّ بَصَرُهُ، فَأغْمَضَهُ، ثُمَّ قَالَ: ((إنَّ الرُّوحَ إِذَا قُبِضَ، تَبِعَهُ البَصَرُ)) فَضَجَّ نَاسٌ مِنْ أهْلِهِ، فَقَالَ: ((لاَ تَدْعُوا عَلَى أنْفُسِكُمْ إِلاَّ بِخَيْرٍ، فَإنَّ المَلاَئِكَةَ يَؤمِّنُونَ عَلَى مَا تَقُولُونَ)) ثُمَّ قَالَ: ((اللَّهُمَّ اغْفِرْ لأَبِي سَلَمَة، وَارْفَعْ دَرَجَتْهُ في المَهْدِيِّينَ، وَاخْلُفْهُ في عَقِبهِ في الغَابِرِينَ، وَاغْفِرْ لَنَا وَلَهُ يَا رَبَّ العَالَمِينَ، وَافْسَحْ لَهُ في قَبْرِهِ، وَنَوِّرْ لَهُ فِيهِ)) رواه مسلم.",
     "no": "1/52"
    }
   }
  },
  "bab-152": {
   "nama": "152- باب ما يقال عند الميت وَمَا يقوله من مات له ميت",
   "urutan": 152,
   "segmen": {
    "1": {
     "arab": "عن أُم سَلَمة رضي اللهُ عنها، قالت: قَالَ رسول الله : ((إِذَا حَضَرتُمُ المَرِيضَ أَو المَيِّتَ، فَقُولُوا خَيْراً، فَإنَّ المَلائِكَةَ يُؤَمِّنُونَ عَلَى مَا تَقُولُونَ))، قالت: فَلَمَّا مَاتَ أَبُو سلَمة، أتَيْتُ النَّبيَّ ، فقلت: يَا رسولَ الله، إنَّ أَبَا سَلَمَة قَدْ مَاتَ، قَالَ: ( قُولِي: اللَّهُمَّ اغْفِرْ لِي وَلَهُ، وَأعْقِبْنِي مِنْهُ عُقْبى حَسَنَةً ) فقلتُ، فَأعْقَبنِي اللهُ مَنْ هُوَ خَيْرٌ لِي مِنْهُ: مُحَمَّداً . رواه مسلم هكَذا: (إِذَا حَضَرتُمُ المَريضَ، أَو المَيِّتَ)، عَلَى الشَّكِّ، ورواه أَبُو داود وغيره: (الميت) بلا شَكّ.",
     "no": "1/53"
    },
    "2": {
     "arab": "وعنها، قالت: سَمِعْتُ رسولَ الله ، يقول: ((مَا مِنْ عَبْدٍ تُصيبُهُ مُصِيبَةٌ، فَيَقُولُ: إنّا للهِ وَإنَّا إِلَيْهِ رَاجِعُونَ، اللَّهُمَّ أُجِرْنِي في مُصِيبَتي وَاخْلفْ لِي خَيراً مِنْهَا، إِلاَّ أَجَرَهُ اللهُ تَعَالَى في مُصِيبَتِهِ وَأخْلَفَ لَهُ خَيْراً مِنْهَا)) قالت: فَلَمَّا تُوُفِّيَ أَبُو سَلَمَة قلتُ كَمَا أمَرَني رسولُ الله ، فَأخْلَفَ اللهُ لِي خَيْراً مِنْهُ رسولَ الله . رواه مسلم.",
     "no": "2/54"
    },
    "3": {
     "arab": "وعن أَبي هريرة ، أنَّ رسول الله ، قَالَ: ((يقولُ اللهُ تَعَالَى: مَا لِعَبْدِي المُؤمِن عِنْدِي جَزَاءٌ إِذَا قَبَضْتُ صَفِيَّهُ مِنْ أهْل الدُّنْيَا، ثُمَّ احْتَسَبَهُ إِلاَّ الجَنَّةَ)) رواه البخاري.",
     "no": "3/55"
    }
   }
  },
  "bab-153": {
   "nama": "153- باب جواز البكاء عَلَى الميت بغير ندب وَلاَ نياحة",
   "urutan": 153,
   "segmen": {
    "1": {
     "arab": "عن ابن عمر رضي الله عنهما: أنَّ رسول الله  عاد سَعْدَ بْنَ عُبَادَةَ، وَمَعَهُ عَبدُ الرَّحْمانِ بْنُ عَوفٍ، وَسَعدُ بْنُ أَبي وَقَّاصٍ، وَعَبْدُ اللهِ بْنُ مَسْعُودٍ ، فَبَكَى رسولُ الله ، فَلَمَّا رَأى القَوْمُ بُكَاءَ رسولِ الله  بَكَوْا، فَقَالَ: ((ألاَ تَسْمَعُونَ ؟ إنَّ الله لاَ يُعَذِّبُ بِدَمْعِ العَينِ، وَلاَ بِحُزنِ القَلبِ، وَلَكِنْ يُعَذِّبُ بِهذَا أَوْ يَرْحَمُ)) وَأشَارَ إِلَى لِسَانِهِ. متفقٌ عَلَيْهِ.",
     "no": "1/56"
    },
    "2": {
     "arab": "وعن أُسَامَة بن زَيدٍ رضي اللهُ عنهما: أنَّ رسول الله  رُفِعَ إِلَيْهِ ابنُ ابْنَتِهِ وَهُوَ فِي المَوتِ، فَفَاضَتْ عَيْنَا  رسولِ اللهِ ، فَقَالَ لَهُ سَعدٌ: مَا هَذَا يَا رسولَ الله ؟! قَالَ: ((هذِهِ رَحْمَةٌ جَعَلَهَا اللهُ تَعَالَى في قُلُوبِ عِبَادِهِ، وَإنَّمَا يَرْحَمُ اللهُ مِنْ عِبَادِهِ الرُّحَمَاءَ)) متفقٌ عَلَيْهِ.",
     "no": "2/57"
    }
   }
  },
  "bab-154": {
   "nama": "154- باب الكف عن مَا يرى من الميت من مكروه",
   "urutan": 154,
   "segmen": {
    "1": {
     "arab": "وعن أَبي رافع أسلم مولى رسول الله : أنَّ رسول الله ، قَالَ: ((مَنْ غَسَّلَ مَيتاً فَكَتَمَ عَلَيْهِ، غَفَرَ اللهُ لَهُ أربَعِينَ مَرَّة)) رواه الحاكم، وقال: صحيح عَلَى شرط مسلم.",
     "no": "1/58"
    }
   }
  },
  "bab-155": {
   "nama": "155- باب الصلاة عَلَى الميت وتشييعه وحضور دفنه وكراهة اتباع النساء الجنائز",
   "urutan": 155,
   "segmen": {
    "1": {
     "arab": "عن أَبي هريرة ، قَالَ: قَالَ رسولُ الله : ((مَنْ شَهِدَ الجَنَازَةَ حَتَّى يُصَلَّى عَلَيْهَا، فَلَهُ قِيراطٌ، وَمَنْ شَهِدَهَا حَتَّى تُدْفَنَ، فَلَهُ قِيرَاطَانِ)) قِيلَ: وَمَا القِيرَاطانِ ؟ قَالَ: ((مِثْلُ الجَبَلَيْنِ العَظِيمَيْنِ)) متفقٌ عَلَيْهِ.",
     "no": "1/59"
    },
    "2": {
     "arab": "وعنه: أنَّ رسولَ الله ، قَالَ: ((مَنِ اتَّبَعَ جَنَازَةَ مُسْلِمٍ إيماناً وَاحْتِسَاباً، وَكَانَ مَعَهُ حَتَّى يُصَلَّى عَلَيْهَا وَيُفرَغَ مِنْ دَفْنِهَا، فَإنَّهُ يَرْجعُ مِنَ الأَجْرِ بِقيراطَيْنِ كُلُّ قِيرَاطٍ مِثْلُ أُحُدٍ، وَمَنْ صَلَّى عَلَيْهَا، ثُمَّ رَجَعَ قَبْلَ أنْ تُدْفَنَ، فَإنَّهُ يَرْجِعُ بِقيرَاطٍ)) رواه البخاري.",
     "no": "2/60"
    },
    "3": {
     "arab": "وعن أم عطية رضي الله عنها، قالت: نُهِينَا عَنِ اتِّبَاعِ الجَنَائِزِ، وَلَمْ يُعْزَمْ عَلَيْنَا. متفقٌ عَلَيْهِ. ومعناه: وَلَمْ يُشَدَّدْ في النَّهْيِ كَمَا يُشَدَّدُ في المُحَرَّمَاتِ.",
     "no": "3/61"
    }
   }
  },
  "bab-156": {
   "nama": "156- باب استحباب تكثير المصلين عَلَى الجنازة وجعل صفوفهم ثلاثة فأكثر",
   "urutan": 156,
   "segmen": {
    "1": {
     "arab": "عن عائشة رضي الله عنها، قالت: قَالَ رسولُ الله : ((مَا مِنْ مَيتٍ يُصَلِّي عَلَيْهِ أُمَّةٌ مِنَ المُسْلِمِينَ يَبْلُغُونَ مِئَةً كُلُّهُمْ يَشْفَعُونَ لَهُ إِلاَّ شُفِّعُوا فِيهِ)) رواه مسلم.",
     "no": "1/62"
    },
    "2": {
     "arab": "وعن ابن عباسٍ رضي الله عنهما، قَالَ: سَمِعْتُ رسول الله ، يقول: ((مَا مِنْ رَجُلٍ مُسْلِمٍ يَمُوتُ، فَيقومُ عَلَى جَنَازَتِهِ أرْبَعُونَ رَجُلاً لاَ يُشْرِكُونَ بِاللهِ شَيْئاً، إِلاَّ شَفَّعَهُمُ اللهُ فِيهِ)) رواه مسلم.",
     "no": "2/63"
    },
    "3": {
     "arab": "وعن مرثدِ بن عبدِ الله اليَزَنِيِّ، قَالَ: كَانَ مَالِكُ بن هُبَيْرَة  إِذَا صَلَّى عَلَى الجَنَازَةِ، فَتَقَالَّ النَّاس عَلَيْهَا، جَزَّأَهُمْ عَلَيْهَا ثَلاَثَةَ أجْزَاءٍ، ثُمَّ قَالَ: قَالَ رسول الله : ((مَنْ صَلَّى عَلَيْهِ ثَلاَثَةُ صُفُوفٍ فَقَدْ أوْجَبَ)) رواه أَبُو داود والترمذي، وقال: ((حديث حسن)).",
     "no": "3/64"
    }
   }
  },
  "bab-157": {
   "nama": "157- باب مَا يقرأ في صلاة الجنازة",
   "urutan": 157,
   "segmen": {
    "1": {
     "arab": "عن أَبي عبد الرحمان عوف بن مالك ، قَالَ: صَلَّى رسول الله  عَلَى جَنازَةٍ، فَحَفِظْتُ مِنْ دُعَائِهِ، وَهُوَ يقُولُ: ((اللَّهُمَّ اغْفِرْ لَهُ وَارْحَمْهُ، وَعَافِهِ وَاعْفُ عَنْهُ، وَأكْرِمْ نُزُلَهُ، وَوَسِّعْ مُدْخَلَهُ، وَاغْسِلْهُ بِالمَاءِ وَالثَّلْجِ وَالبَرَدِ، وَنَقِّه مِن الخَطَايَا كَمَا نَقَّيْتَ الثَّوْبَ الأَبْيَضَ مِنَ الدَّنَس، وَأبدلْهُ دَاراً خَيْراً مِنْ دَارِهِ، وَأهْلاً خَيراً مِنْ أهْلِهِ، وَزَوْجَاً خَيْراً مِنْ زَوْجِهِ، وَأدْخِلهُ الجَنَّةَ، وَأعِذْهُ مِنْ عَذَابِ القَبْرِ، وَمنْ عَذَابِ النَّارِ)) حَتَّى تَمَنَّيتُ أن أكُون أنَا ذَلِكَ الْمَيِّت. رواه مسلم.",
     "no": "1/65"
    },
    "2": {
     "arab": "وعن أَبي هريرة وأبي قتادة وَأبي إبراهيم الأشهلي، عن أبيه - وأبوه صَحَابيٌّ - ، عن النبيِّ : أنَّهُ صَلَّى عَلَى جَنَازَةٍ، فَقَالَ: ((اللَّهُمَّ اغْفِرْ لِحَيِّنَا وَمَيِّتِنَا، وَصَغِيرنَا وَكَبيرنَا، وَذَكَرِنَا وَأُنْثَانَا، وشَاهِدنَا وَغَائِبِنَا، اللَّهُمَّ مَنْ أحْيَيْتَهُ مِنَّا فَأحْيِهِ عَلَى الإسْلاَمِ، وَمَنْ تَوَفَّيْتَهُ مِنَّا فَتَوفَّهُ عَلَى الإيمَان، اللَّهُمَّ لاَ تَحْرِمْنَا أجْرَهُ، وَلاَ تَفْتِنَّا بَعدَهُ)) رواه الترمذي    من رواية أَبي هريرة والأشهلي. ورواه أَبُو داود من رواية أَبي هريرة وأبي قتادة. قَالَ الحاكم: ((حديث أَبي هريرة صحيح عَلَى شرط البخاري ومسلم))، قَالَ الترمذي: ((قَالَ البخاري: أصَحُّ رواياتِ هَذَا الحديث رواية الأشْهَلِيِّ، قَالَ البخاري: وأصح شيء في هَذَا الباب حديث عَوْفِ ابن مَالِكٍ)).",
     "no": "2/66"
    },
    "3": {
     "arab": "وعنه، عن النبيِّ  في الصَّلاَةِ عَلَى الجَنَازَةِ: ((اللَّهُمَّ أنْتَ رَبُّهَا، وَأنْتَ خَلَقْتَهَا، وَأنتَ هَدَيْتَهَا للإسْلاَمِ، وَأنتَ قَبَضْتَ رُوحَهَا، وَأنْتَ أعْلَمُ بِسرِّهَا وَعَلاَنِيَتِهَا، وَقَدْ جِئنَاكَ شُفَعَاءَ لَهُ، فَاغْفِرْ لَهُ)) رواه أَبُو داود.",
     "no": "3/67"
    }
   }
  },
  "bab-158": {
   "nama": "158- باب الإسراع بالجنازة",
   "urutan": 158,
   "segmen": {
    "1": {
     "arab": "عن أَبي هريرة ، عن النبيِّ ، قَالَ: ((أسْرِعُوا بالجَنَازَةِ، فَإنْ تَكُ صَالِحَةً، فَخَيرٌ تُقَدِّمُونَهَا إِلَيْهِ، وَإنْ تَكُ سِوَى ذَلِكَ، فَشَرٌّ تَضَعُونَهُ عَنْ رِقَابِكُمْ)) متفقٌ عَلَيْهِ. وفي روايةٍ لمسلمٍ: ((فَخَيْرٌ تُقَدِّمُونَهَا عَلَيْهِ)).",
     "no": "1/68"
    },
    "2": {
     "arab": "وعن أَبي سعيد الخدري ، قَالَ: كَانَ النبي ، يقُولُ: ((إِذَا وُضِعَت الجَنَازَةُ، فَاحْتَمَلَهَا الرِّجَالُ عَلَى أعنَاقِهمْ، فَإنْ كَانَتْ صَالِحَةً، قالتْ: قَدِّمُونِي، وَإنْ كَانَتْ غَيْرَ صَالِحَةٍ، قَالَتْ لأَهْلِهَا: يَا وَيْلَهَا أَيْنَ تَذْهَبُونَ بِهَا ؟ يَسْمَعُ صَوْتَهَا  كُلُّ شَيْءٍ إِلاَّ الإنْسَانَ، وَلَوْ سَمِعَ الإنسَانُ لَصَعِقَ)) رواه البخاري.",
     "no": "2/69"
    }
   }
  },
  "bab-159": {
   "nama": "159- باب تعجيل قضاء الدَّين عن الميت والمبادرة إِلَى تجهيزه إلا أن يموت فجأة فيترك حَتَّى يُتَيَقَّنَ مَوْتُه",
   "urutan": 159,
   "segmen": {
    "1": {
     "arab": "عن أَبي هريرة ، عن النبي ، قَالَ: ((نَفْسُ المُؤْمِنِ مُعَلَّقَةٌ بِدَيْنِهِ حَتَّى يُقْضى عَنْهُ)) رواه الترمذي، وقال: ((حديث حسن)).",
     "no": "1/70"
    },
    "2": {
     "arab": "وعن حُصَيْنِ بن وَحْوَحٍ : أنَّ طَلْحَةَ بْنَ البَرَاءِ بن عَازِبٍ رضي الله عنهما مَرِضَ، فَأتَاهُ النَّبيُّ  يَعُودُهُ، فَقَالَ: ((إنِّي لاَ أرى طَلْحَةَ إِلاَّ قَدْ حَدَثَ فِيهِ المَوْتُ، فآذِنُوني بِهِ وَعَجِّلُوا بِهِ، فَإنَّهُ لاَ يَنْبَغِي لجِيفَةِ مُسْلِمٍ أنْ تُحْبَسَ بَيْنَ ظَهْرَانِيْ أهْلِهِ)) رواه أَبُو داود.",
     "no": "2/71"
    }
   }
  },
  "bab-160": {
   "nama": "160- باب الموعظة عند القبر",
   "urutan": 160,
   "segmen": {
    "1": {
     "arab": "عن عَلِيٍّ ، قَالَ: كُنَّا فِي جَنَازَةٍ في بَقيعِ الغَرْقَدِ، فَأتَانَا رسولُ الله  فَقَعَدَ، وَقَعَدْنَا حَوْلَهُ وَمَعَهُ مِخْصَرَةٌ، فَنَكَّسَ وَجَعَلَ يَنْكُتُ بِمِخْصَرَتِهِ، ثُمَّ قَالَ: ((مَا مِنْكُمْ مِنْ أحَدٍ إِلاَّ وَقَدْ كُتِبَ مَقْعَدُهُ مِنَ النَّارِ وَمَقْعَدُهُ مِنَ الجَنَّةِ)) فقالوا: يَا رسولَ الله، أفَلا نَتَّكِلُ عَلَى كِتَابنَا ؟ فَقَالَ: ((اعْمَلُوا ؛ فكلٌّ مُيَسرٌ لِمَا خُلِقَ لَهُ)) وذكَر تَمَامَ الحديث. متفقٌ عَلَيْهِ.",
     "no": "1/72"
    }
   }
  },
  "bab-161": {
   "nama": "161- باب الدعاء للميت بعد دفنه والقعود عند قبره ساعة للدعاء لَهُ والاستغفار والقراءة",
   "urutan": 161,
   "segmen": {
    "1": {
     "arab": "وعن أَبي عمرو - وقيل: أَبُو عبد الله، وقيل: أَبُو ليلى - عثمان بن عفان ، قَالَ: كَانَ النبيُّ  إِذَا فُرِغَ مِن دَفْنِ المَيِّتِ وَقَفَ عَلَيْهِ، وقال: ((اسْتَغْفِرُوا لأخِيكُمْ وَسَلُوا لَهُ التَّثْبِيتَ، فَإنَّهُ الآنَ يُسألُ)) رواه أَبُو داود.",
     "no": "1/73"
    },
    "2": {
     "arab": "وعن عمرو بن العاص ، قَالَ: إِذَا دَفَنْتُمُونِي، فَأقِيمُوا حَوْلَ قَبْرِي قَدْرَ مَا تُنْحَرُ جَزُورٌ، وَيُقَسَّمُ لَحمُهَا حَتَّى أَسْتَأنِسَ بِكُمْ، وَأعْلَمَ مَاذَا أُرَاجِعُ بِهِ رُسُلَ رَبِّي. رواه مسلم. وَقَدْ سبق بطوله.",
     "no": "2/74"
    }
   }
  },
  "bab-162": {
   "nama": "162- باب الصدقة عن الميت والدعاء لَهُ",
   "urutan": 162,
   "segmen": {
    "1": {
     "arab": "وعن عائشة رضي الله عنها: أنَّ رجلاً قَالَ للنبيِّ : إنَّ أُمِّي افْتُلِتَتْ نَفْسُهَا وَأُرَاهَا لَوْ تَكَلَّمَتْ تَصَدَّقَتْ، فَهَلْ لَهَا أجْرٌ إنْ تَصَدَّقْتُ عَنْهَا ؟ قَالَ: ((نَعَمْ)) متفقٌ عَلَيْهِ.",
     "no": "1/75"
    },
    "2": {
     "arab": "وعن أَبي هريرة : أنَّ رسول الله ، قَالَ: ((إِذَا مَاتَ الإنْسَانُ انْقَطَعَ عَمَلُهُ إِلاَّ مِنْ ثَلاثٍ: صَدَقةٍ جَاريَةٍ، أَوْ عِلْمٍ يُنْتَفَعُ بِهِ، أَوْ وَلَدٍ صَالِحٍ يَدْعُو لَهُ)) رواه مسلم.",
     "no": "2/76"
    }
   }
  },
  "bab-163": {
   "nama": "163- باب ثناء الناس عَلَى الميت",
   "urutan": 163,
   "segmen": {
    "1": {
     "arab": "عن أنسٍ ، قَالَ: مَرُّوا بِجَنَازَةٍ، فَأَثْنَوْا عَلَيْهَا خَيْراً، فَقَالَ النبيُّ : ((وَجَبَتْ)) ثُمَّ مَرُّوا بِأُخْرَى، فَأثْنَوْا عَلَيْهَا شَرّاً، فَقَالَ النبي : ((وَجَبَتْ))، فَقَالَ عمر بن الخطاب : مَا وَجَبَت ؟ فَقَالَ: ((هَذَا أثْنَيْتُمْ عَلَيْهِ خَيْراً، فَوَجَبتْ لَهُ الجَنَّةُ، وهَذَا أثْنَيْتُمْ عَلَيْهِ شَرّاً، فَوَجَبَتْ لَهُ النَّار، أنْتُمْ شُهَدَاءُ اللهِ في الأَرضِ)) متفقٌ عَلَيْهِ.",
     "no": "1/77"
    },
    "2": {
     "arab": "وعن أَبي الأسْوَدِ، قَالَ: قَدِمْتُ المَدِينَةَ، فَجَلَسْتُ إِلَى عُمَرَ بنِ الخَطَّاب  فَمَرَّتْ بِهمْ جَنَازَةٌ، فَأُثْنِيَ عَلَى صَاحِبِهَا خَيْراً، فَقَالَ عُمَرُ: وَجَبَتْ، ثُمَّ مُرَّ بَأُخْرَى فَأُثْنِيَ عَلَى صَاحِبِهَا خَيْراً، فَقَالَ عُمرُ: وَجَبَتْ، ثُمَّ مُرَّ بِالثَّالِثَةِ، فَأُثْنِيَ عَلَى صَاحِبِهَا شَرّاً، فَقَالَ عُمر: وَجَبَتْ، قَالَ أَبُو الأسودِ: فقلتُ: وَمَا وَجَبَتْ يَا أمْيرَ المُؤمِنينَ ؟ قَالَ: قُلْتُ كما قَالَ النبي : ((أيُّمَا مُسْلِمٍ شَهِدَ لَهُ أرْبَعَةٌ بِخَيرٍ، أدْخَلَهُ اللهُ الجَنَّةَ)) فقُلْنَا: وَثَلاثَةٌ ؟ قَالَ: ((وَثَلاثَةٌ)) فقلنا: وَاثْنَانِ ؟ قَالَ: ((وَاثْنَانِ)) ثُمَّ لَمْ نَسْأَلْهُ عَن الواحِدِ. رواه البخاري.",
     "no": "2/78"
    }
   }
  },
  "bab-164": {
   "nama": "164- باب فضل من مات لَهُ أولاد صغار",
   "urutan": 164,
   "segmen": {
    "1": {
     "arab": "وعن أنسٍ ، قَالَ: قَالَ رسول الله : ((مَا مِنْ مُسْلِمٍ يَمُوتُ لَهُ ثَلاَثَةٌ لَمْ يَبْلُغوا الحِنْثَ إِلاَّ أدْخَلَهُ اللهُ الجَنَّةَ بِفَضْلِ رَحْمَتِهِ إيَّاهُمْ)) متفقٌ عَلَيْهِ.",
     "no": "1/79"
    },
    "2": {
     "arab": "وعن أَبي سعيد الخدري ، قَالَ: جَاءتِ امْرأةٌ إِلَى رسولِ الله ، فَقَالَتْ: يَا رسولَ الله، ذَهبَ الرِّجَالُ بِحَدِيثكَ، فَاجْعَلْ لَنَا مِنْ نَفْسِكَ يَوْماً نَأتِيكَ فِيهِ تُعَلِّمُنَا مِمَّا عَلَّمَكَ اللهُ، قَالَ: ((اجْتَمِعْنَ يَوْمَ كَذَا وَكَذَا)) فَاجْتَمَعْنَ، فَأَتَاهُنَّ النبيُّ  فَعَلَّمَهُنَّ مِمَّا عَلَّمَهُ اللهُ، ثُمَّ قَالَ: ((مَا مِنْكُنَّ مِنِ امْرَأةٍ تُقَدِّمُ ثَلاَثَةً مِنَ الوَلَدِ إِلاَّ كَانُوا لَهَا حِجَاباً مِنَ النَّارِ)) فقالتِ امْرَأةٌ: وَاثْنَينِ ؟ فَقَالَ رسولُ الله : ((وَاثْنَيْنِ)) متفقٌ عَلَيْهِ.",
     "no": "2/80"
    }
   }
  },
  "bab-165": {
   "nama": "165- باب البكاء والخوف عِنْدَ المرور بقبور الظالمين ومصارعهم وإظهار الافتقار إِلَى الله تَعَالَى والتحذير من الغفلة عن ذلك",
   "urutan": 165,
   "segmen": {
    "1": {
     "arab": "عن ابن عمرَ رضي الله عنهما: أنَّ رسول الله  قَالَ لأصْحَابِهِ - يعْني لَمَّا وَصَلُوا الحِجْرَ - دِيَارَ ثَمُودَ -: ((لاَ تَدْخُلُوا عَلَى هَؤُلاَءِ المُعَذَّبِينَ إِلاَّ أنْ تَكُونُوا بَاكِينَ، فَإنْ لَمْ تَكُونُوا بَاكِينَ، فَلاَ تَدْخُلُوا عَلَيْهِمْ، لاَ يُصِيبُكُمْ مَا أصَابَهُمْ)) متفقٌ عَلَيْهِ. وفي روايةٍ قَالَ: لَمَّا مَرَّ رسولُ الله  بِالحِجْرِ، قَالَ: ((لاَ تَدْخُلُوا مَسَاكِنَ الَّذِينَ ظَلَمُوا أنْفُسَهُمْ، أنْ يُصِيبَكُمْ مَا أصَابَهُمْ، إِلاَّ أنْ تَكُونُوا بَاكِينَ)) ثُمَّ قَنَّع رسولُ الله ، رَأسَهُ وأسْرَعَ السَّيْرَ حَتَّى أجَازَ الوَادِي.",
     "no": "1/81"
    }
   }
  },
  "bab-166": {
   "nama": "166- باب استحباب الخروج يوم الخميس واستحبابه أول النهار",
   "urutan": 166,
   "segmen": {
    "1": {
     "arab": "عن كعب بن مالك : أنَّ النبيَّ  خَرَجَ في غَزْوَةِ تَبُوكَ يَوْمَ الخَمِيس، وَكَانَ يُحِبُّ أنْ يَخْرُجَ يَوْمَ الْخَميسِ. متفقٌ عَلَيْهِ. وفي رواية في الصحيحين: لقَلَّمَا كَانَ رسولُ الله  يَخْرُجُ إِلاَّ في يَوْمِ الخَمِيسِ.",
     "no": "1/82"
    },
    "2": {
     "arab": "وعن صخر بن وَداعَةَ الغامِدِيِّ الصحابيِّ : أنَّ رسولَ الله ، قَالَ: ((اللَّهُمَّ بَارِكْ لأُمَّتِي في بُكُورِهَا)) وَكَانَ إِذَا بَعَثَ سَرِيَّةً أَوْ جَيْشَاً بَعَثَهُمْ مِنْ أوَّلِ النَّهَارِ. وَكَانَ صَخْرٌ تَاجِراً، وَكَانَ يَبْعَثُ تِجَارَتَهُ أوَّلَ النَّهَار، فَأَثْرَى وَكَثُرَ مَالُهُ. رواه أَبُو داود والترمذي، وقال: ((حديث حسن)).",
     "no": "2/83"
    }
   }
  },
  "bab-167": {
   "nama": "167- باب استحباب طلب الرفقة وتأميرهم عَلَى أنفسهم واحداً يطيعونه",
   "urutan": 167,
   "segmen": {
    "1": {
     "arab": "عن ابن عمرَ رضي اللهُ عنهما، قَالَ: قَالَ رسولُ الله : ((لَوْ أنَّ النَّاسَ يَعْلَمُونَ مِنَ الوحدَةِ مَا أعْلَمُ، مَا سَارَ رَاكبٌ بِلَيْلٍ وَحْدَهُ !)) رواه البخاري.",
     "no": "1/84"
    },
    "2": {
     "arab": "وعن أَبي سعيد وأبي هُريرة رضي اللهُ تَعَالَى عنهما، قالا: قَالَ رسولُ الله : ((إِذَا خَرَجَ ثَلاَثَةٌ في سَفَرٍ فَليُؤَمِّرُوا أحَدَهُمْ)) حديث حسن، رواه أَبُو داود بإسنادٍ حسن.",
     "no": "2/85"
    }
   }
  },
  "bab-168": {
   "nama": "168- باب آداب السير والنزول والمبيت والنوم في السفر واستحباب السُّرَى والرفق بالدواب ومراعاة مصلحتها وأمر من قصّر في حقها بالقيام بحقها وجواز الإرداف عَلَى الدابة إِذَا كانت تطيق ذلك",
   "urutan": 168,
   "segmen": {
    "1": {
     "arab": "عن أَبي هُريرةَ ، قَالَ: قَالَ رسولُ الله : ((إِذَا سَافَرْتُمْ فِي الخِصْبِ، فَأعْطُوا الإبلَ حَظَّهَا مِنَ الأَرْضِ، وَإِذَا سَافَرْتُمْ في الجدْبِ، فَأسْرِعُوا عَلَيْهَا السَّيْرَ، وَبَادِرُوا بِهَا نِقْيَهَا، وَإِذَا عَرَّسْتُمْ، فَاجْتَنِبُوا الطَّرِيقَ ؛ فَإنَّهَا طُرُقُ الدَّوَابِّ، وَمَأوَى الهَوَامِّ بِاللَّيْلِ)) رواه مسلم.  مَعنَى ((أعْطُوا الإبِلَ حَظَّهَا مِنَ الأرْضِ)) أيْ: ارْفُقُوا بِهَا في السَّيْرِ لِتَرْعَى في حَالِ سَيرِهَا، وَقوله: ((نِقْيَهَا)) هُوَ بكسر النون وإسكان القاف وبالياءِ المثناة من تَحْت وَهُوَ: المُخُّ، معناه: أسْرِعُوا بِهَا حَتَّى تَصِلُوا المَقصِدَ قَبْلَ أنْ يَذْهَبَ مُخُّهَا مِنْ ضَنْك السَّيْرِ. وَ((التَّعْرِيسُ)): النُزولُ في اللَّيلِ.",
     "no": "1/86"
    },
    "2": {
     "arab": "وعن أنس ، قَالَ: قَالَ رسول الله : ((عَلَيْكُمْ بِالدُّلْجَةِ، فَإنَّ الأرْضَ تُطْوَى بِاللَّيْلِ)) رواه أَبُو داود بإسناد حسن. ((الدُّلْجَةُ)): السَّيْرُ في اللَّيْلِ.",
     "no": "2/87"
    },
    "3": {
     "arab": "وعن سهل بن عمرو وقيل: سهل بن الربيع بن عمرو الأنصاري المعروف بابن الحنظلِيَّة، وَهُوَ من أهل بيعة الرِّضْوَانِ ، قَالَ: مَرَّ رسولُ الله  بِبَعِيرٍ قَدْ لَحِقَ ظَهْرُهُ بِبَطْنِهِ، فَقَالَ: ((اتَّقُوا الله في هذِهِ البَهَائِمِ المُعجَمَةِ، فَارْكَبُوهَا صَالِحَةً، وَكُلُوهَا صَالِحَةً)) رواه أَبُو داود بإسناد صحيح.",
     "no": "3/88"
    }
   }
  },
  "bab-169": {
   "nama": "169- باب إعانة الرفيق",
   "urutan": 169,
   "segmen": {
    "1": {
     "arab": "وعن أَبي سعيد الخدري ، قَالَ: بَيْنَمَا نَحْنُ في سَفَرٍ إذْ جَاءَ رَجُلٌ عَلَى رَاحِلَةٍ لَهُ، فَجَعَلَ يَصْرِفُ بَصَرَهُ يَمِيناً وَشِمَالاً، فَقَالَ رسولُ الله : ((مَنْ كَانَ مَعَهُ فَضْلُ ظَهْرٍ فَلْيَعُدْ بِهِ عَلَى مَنْ لاَ ظَهْرَ لَهُ، وَمَنْ كَانَ لَهُ فَضْلُ زَادٍ فَلْيَعُدْ بِهِ عَلَى مَنْ لاَ زَادَ لَهُ))، فَذَكَرَ مِنْ أصْنَافِ المَالِ مَا ذَكَرَهُ، حَتَّى رَأيْنَا، أنَّهُ لاَ حَقَّ لأَحَدٍ مِنَّا فِي فَضْلٍ. رواه مسلم.",
     "no": "1/89"
    }
   }
  },
  "bab-170": {
   "nama": "170- باب مَا يقول إذا ركب دَابَّة للسفر",
   "urutan": 170,
   "segmen": {
    "1": {
     "arab": "وعن ابن عمر رضي الله عنهما: أنَّ رسول الله  كَانَ إِذَا اسْتَوَى عَلَى بَعِيرِهِ خَارِجاً إِلَى سَفَرٍ، كَبَّرَ ثَلاثاً، ثُمَّ قَالَ: ((سُبْحَانَ الَّذِي سَخَّرَ لَنَا هَذَا وَمَا كُنَّا لَهُ مُقْرِنِينَ، وَإنَّا إِلَى رَبِّنَا لَمُنْقَلبُونَ. اللّهُمَّ إنا نسألكَ في سفرنا هذا البرّ والتَّقوى، ومنَ العملِ ما ترضى، اللَّهُمَّ هَوِّن عَلَيْنَا سَفَرَنَا هَذَا، وَاطْوِ عَنَّا بُعْدَهُ. اللَّهُمَّ أنْتَ الصَّاحِبُ في السَّفَرِ، والخَلِيفَةُ في الأهْلِ. اللَّهُمَّ إنِّي أعُوذُ بِكَ مِنْ وَعْثَاءِ السَّفَرِ، وَكَآبَةِ المَنْظَرِ، وَسُوءِ المُنْقَلَبِ في المالِ وَالأَهْلِ وَالوَلَدِ)) وَإِذَا رَجَعَ قَالَهُنَّ وَزَادَ فِيهِنَّ: ((آيِبُونَ، تَائِبُونَ، عَابِدُونَ، لِرَبِّنَا حَامِدُونَ)) رواه مسلم.",
     "no": "1/90"
    },
    "2": {
     "arab": "وعن عَلِي بن ربيعة، قَالَ: شهدت عليَّ بن أَبي طالب ، أُتِيَ بِدَابَّةٍ لِيَرْكَبَهَا، فَلَمَّا وَضَعَ رِجْلَهُ في الرِّكَابِ، قَالَ: بِسْمِ اللهِ، فَلَمَّا اسْتَوَى عَلَى ظَهْرِهَا، قَالَ: الحَمْدُ للهِ الَّذِي سَخَّرَ لَنَا هَذَا وَمَا كُنَّا لَهُ مُقْرِنينَ، وَإنَّا إِلَى رَبِّنَا لَمُنْقَلِبُونَ، ثُمَّ قَالَ: الحمْدُ للهِ، ثَلاثَ مَرَّاتٍ، ثُمَّ قَالَ: اللهُ أكْبَرُ، ثَلاثَ مَرَّاتٍ، ثُمَّ قَالَ: سُبْحَانَكَ إنّي ظَلَمْتُ نَفْسِي فَاغْفِرْ لِي إنَّهُ لاَ يَغْفِرُ الذُّنُوبَ إِلاَّ أنْتَ، ثُمَّ ضَحِكَ، فَقيلَ: يَا أمِيرَ المُؤمِنِينَ، مِنْ أيِّ شَيْءٍ ضَحِكْتَ ؟ قَالَ: رَأيتُ النبيَّ  فَعَلَ كَمَا فَعَلْتُ ثُمَّ ضَحِكَ، فقُلْتُ: يَا رسول اللهِ، مِنْ أيِّ شَيْءٍ ضَحِكْتَ ؟ قَالَ: ((إنَّ رَبَّكَ تَعَالَى يَعْجَبُ مِنْ عَبدِهِ إِذَا قَالَ: اغْفِرْ لِي ذُنُوبِي، يَعْلَمُ أنَّهُ لاَ يَغْفِرُ الذُّنُوبَ غَيْرِي)) رواه أَبُو داود والترمذي، وقال: ((حديث حسن))، وفي بعض النسخ: ((حسن صحيح)). وهذا لفظ أَبي داود.",
     "no": "2/91"
    }
   }
  },
  "bab-171": {
   "nama": "171- باب تكبير المسافر إِذَا صعد الثنايا وشبهها وتسبيحه إِذَا هبط الأودية ونحوها، والنهي عن المبالغة برفع الصوتِ بالتكبير ونحوه",
   "urutan": 171,
   "segmen": {
    "1": {
     "arab": "عن جابر ، قَالَ: كُنَّا إِذَا صَعِدْنَا كَبَّرْنَا، وَإِذَا نَزَلْنَا سَبَّحْنَا. رواه البخاري.",
     "no": "1/92"
    },
    "2": {
     "arab": "وعنه، قَالَ: كَانَ النَّبي  إِذَا قَفَلَ مِنَ الحَجِّ أَوْ العُمْرَةِ، كُلَّمَا أوْفَى عَلَى ثَنِيَّةٍ أَوْ فَدْفَدٍ كَبَّرَ ثَلاثَاً، ثُمَّ قَالَ: ((لاَ إلهَ إِلاَّ اللهُ وَحْدَهُ لاَ شَرِيكَ لَهُ، لَهُ المُلْكُ وَلَهُ الحَمْدُ، وَهُوَ عَلَى كُلِّ شَيْءٍ قَدِيرٌ. آيِبُونَ، تَائِبُونَ، عَابِدُونَ، سَاجِدُونَ، لِرَبِّنَا حَامِدُونَ، صَدَقَ اللهُ وَعْدَهُ، وَنَصَرَ عَبْدَهُ، وَهَزَمَ الأحْزَابَ وَحْدَهُ)) متفقٌ عَلَيْهِ.",
     "no": "2/93"
    },
    "3": {
     "arab": "وعن أَبي موسى الأشعريِّ ، قَالَ: كنّا مَعَ النبيِّ  في سَفَرٍ، فَكُنَّا إِذَا أشْرَفْنَا عَلَى وَادٍ هَلَّلْنَا وَكَبَّرْنَا وَارتَفَعَتْ أصْوَاتُنَا، فَقَالَ النبيُّ : ((يَا أيُّهَا النَّاسُ، ارْبَعُوا عَلَى أنْفُسِكُمْ، فَإنَّكُمْ لاَ تَدْعُونَ أصَمَّ وَلاَ غَائِباً، إنَّهُ مَعَكُمْ، إنَّهُ سَمِيعٌ قَرِيبٌ)) متفقٌ عَلَيْهِ.    ((ارْبَعُوا)) بفتحِ الباءِ الموحدةِ أيْ: ارْفُقُوا بِأَنْفُسِكُمْ.",
     "no": "3/94"
    }
   }
  },
  "bab-172": {
   "nama": "172- باب استحباب الدعاء في السفر",
   "urutan": 172,
   "segmen": {
    "1": {
     "arab": "وعن أَبي هريرة ، قَالَ: قَالَ رسولُ الله : ((ثلاثُ دَعَوَاتٍ مُسْتَجَابَات لاَ شَكَّ فِيهِنَّ: دَعْوَةُ المَظْلُومِ، وَدَعْوَةُ المُسَافِرِ، وَدَعْوَةُ الوَالِدِ عَلَى وَلَدِهِ)) رواه أَبُو داود والترمذي، وقال: ((حديث حسن)). وليس في رواية أَبي داود: ((عَلَى وَلَدِهِ)).",
     "no": "1/95"
    }
   }
  },
  "bab-173": {
   "nama": "173- باب مَا يدعو بِهِ إِذَا خاف ناساً أَوْ غيرهم",
   "urutan": 173,
   "segmen": {
    "1": {
     "arab": "عن أَبي موسى الأشعريِّ : أنَّ رسولَ الله  كَانَ إِذَا خَافَ قَوْماً، قَالَ: ((اللَّهُمَّ إنَّا نَجْعَلُكَ في نُحُورِهِمْ، وَنَعُوذُ بِكَ مِنْ شُرُورِهِمْ)) رواه أَبُو داود والنسائي بإسنادٍ صحيحٍ.",
     "no": "1/96"
    }
   }
  },
  "bab-174": {
   "nama": "174- باب مَا يقول إِذَا نزل منْزلاً",
   "urutan": 174,
   "segmen": {
    "1": {
     "arab": "عن خولة بنتِ حَكِيمٍ رضي الله عنها، قالت: سَمِعْتُ رسولَ اللهِ ، يَقُولُ: ((مَنْ نَزَلَ مَنْزِلاً ثُمَّ قَالَ: أَعُوذُ بِكَلِمَاتِ اللهِ التَّامَّاتِ مِنْ شَرِّ مَا خَلَقَ، لَمْ يَضُرَّهُ شَيْءٌ حَتَّى يَرْتَحِلَ مِنْ مَنْزِلِهِ ذَلِكَ)) رواه مسلم.",
     "no": "1/97"
    },
    "2": {
     "arab": "وعن ابن عمر رضي الله عنهما، قَالَ: كَانَ رسول الله  إِذَا سَافَرَ فَأقْبَلَ اللَّيْلُ، قَالَ: ((يَا أرْضُ، رَبِّي وَرَبُّكِ اللهُ، أعُوذُ بِاللهِ مِنْ شَرِّكِ وَشَرِّ مَا فِيكِ، وَشَرِّ مَا خُلِقَ فِيكِ، وَشَرِّ مَا يَدِبُّ عَلَيْكِ، وَأعُوذُ بِكَ مِنْ شَرِّ أسَدٍ وَأسْوَدٍ، وَمِنَ الحَيَّةِ وَالعَقْرَبِ، وَمِنْ سَاكِنِ البَلَدِ، وَمِنْ وَالِدٍ وَمَا وَلَدَ)) رواه أَبُو داود.   وَ((الأَسْوَدُ)): الشَّخْصُ، قَالَ الخَطَّابِيُّ: وَ((سَاكِنُ البَلَدِ)): هُمُ الجِنُّ الَّذِينَ هُمْ سُكَّانُ الأرْضِ. قَالَ: وَالبَلَد مِنَ الأرْضِ: مَا كَانَ مَأْوَى الحَيَوانِ، وَإنْ لَمْ يَكُنْ فِيهِ بِنَاءٌ وَمَنَازلُ. قَالَ: وَيَحْتَمِلُ أنَّ المُرَادَ: ((بِالوَالِدِ)) إبليسُ: ((وَمَا وَلَدَ)): الشَّيَاطِينُ.",
     "no": "2/98"
    }
   }
  },
  "bab-175": {
   "nama": "175- باب استحباب تعجيل المسافر الرجوع إِلَى أهله إِذَا قضى حاجته",
   "urutan": 175,
   "segmen": {
    "1": {
     "arab": "عن أَبي هريرة : أنَّ رسول الله ، قَالَ: ((السَّفَرُ قِطْعَةٌ مِنَ العَذَابِ، يَمْنَعُ أحَدَكُمْ طَعَامَهُ وَشَرابَهُ وَنَوْمَهُ، فَإذَا قَضَى أحَدُكُمْ نَهْمَتَهُ مِنْ سَفَرِهِ، فَلْيُعَجِّلْ إِلَى أهْلِهِ)) متفقٌ عَلَيْهِ.  ((نَهْمَتهُ)): مَقْصُودهُ.",
     "no": "1/99"
    }
   }
  },
  "bab-176": {
   "nama": "176- باب استحباب القدوم عَلَى أهله نهاراً وكراهته في الليل لغير حاجة",
   "urutan": 176,
   "segmen": {
    "1": {
     "arab": "عن جابر : أنَّ رسولَ الله ، قَالَ: ((إِذَا أطال أحَدُكُمُ الغَيْبَةَ فَلاَ يَطْرُقَنَّ أهْلَهُ لَيْلاً)). وفي روايةٍ: أنَّ رسول الله  نَهَى أنْ يَطْرُقَ الرَّجُلُ أهْلَهُ لَيْلاً. متفقٌ عَلَيْهِ.",
     "no": "1/100"
    },
    "2": {
     "arab": "وعن أنسٍ ، قَالَ: كَانَ رسولُ الله  لا يَطْرُقُ أهْلَهُ لَيْلاً، وَكَانَ يَأتِيهمْ غُدْوَةً أَوْ عَشِيَّةً. متفقٌ عَلَيْهِ. ((الطُّرُوقُ)): المَجيءُ فِي اللَّيْلِ.",
     "no": "2/101"
    }
   }
  },
  "bab-177": {
   "nama": "177- باب مَا يقول إِذَا رجع وإذا رأى بلدته",
   "urutan": 177,
   "segmen": {
    "1": {
     "arab": "وعن أنس ، قَالَ: أقْبَلْنَا مَعَ النَّبيِّ  حَتَّى إِذَا كُنَّا بِظَهْرِ الْمَدِينَةِ، قَالَ: ((آيِبُونَ، تَائِبُونَ، عَابِدُونَ، لِرَبِّنَا حَامِدُونَ)) فَلَمْ يَزَلْ يَقُولُ ذَلِكَ حَتَّى قَدِمْنَا المَدِينَةَ. رواه مسلم.",
     "no": "1/102"
    }
   }
  },
  "bab-178": {
   "nama": "178- باب استحباب ابتداء القادم بالمسجد الذي في جواره وصلاته فيه ركعتين",
   "urutan": 178,
   "segmen": {
    "1": {
     "arab": "عن كعب بن مالِك : أنَّ رسولَ الله  كَانَ إِذَا قَدِمَ مِنْ سَفَرٍ، بَدَأ بِالْمَسْجِدِ فَرَكَعَ فِيهِ رَكْعَتَيْنِ. متفقٌ عَلَيْهِ.",
     "no": "1/103"
    }
   }
  },
  "bab-179": {
   "nama": "179- باب تحريم سفر المرأة وحدها",
   "urutan": 179,
   "segmen": {
    "1": {
     "arab": "عن أَبي هريرة ، قَالَ: قَالَ رسولُ الله : ((لاَ يَحِلُّ لامْرَأَةٍ تُؤْمِنُ بِاللهِ وَالْيَومِ الآخِرِ تُسَافِرُ مَسِيرَةَ يَوْمٍ وَلَيْلَةٍ إِلاَّ مَعَ ذِي مَحْرَمٍ عَلَيْهَا)) متفقٌ عَلَيْهِ.",
     "no": "1/104"
    },
    "2": {
     "arab": "وعن ابن عباس رضي الله عنهما: أنَّهُ سَمِعَ النبيَّ ، يقول: ((لاَ يَخْلُوَنَّ رَجُلٌ بِامْرَأَةٍ إِلاَّ وَمَعَهَا ذُو مَحْرَمٍ، وَلاَ تُسَافِرُ المَرْأةُ إِلاَّ مَعَ ذِي مَحْرَمٍ)) فَقَالَ لَهُ رَجُلٌ: يَا رسولَ الله، إنَّ امْرَأتِي خَرَجَتْ حَاجَّةً، وَإنِّي اكْتُتِبْتُ في غَزْوَةِ كَذَا وَكَذَا ؟ قَالَ: ((انْطَلِقْ فَحُجَّ مَعَ امْرَأَتِكَ)) متفقٌ عَلَيْهِ.",
     "no": "2/105"
    }
   }
  },
  "bab-180": {
   "nama": "180- باب فضل قراءة القرآن",
   "urutan": 180,
   "segmen": {
    "1": {
     "arab": "عن أَبي أُمَامَةَ ، قَالَ: سَمِعْتُ رسولَ اللهِ ، يقول: ((اقْرَؤُوا القُرْآنَ؛ فَإنَّهُ يَأتِي يَوْمَ القِيَامَةِ شَفِيعاً لأَصْحَابِهِ)) رواه مسلم.",
     "no": "1/106"
    },
    "2": {
     "arab": "وعن النَّوَّاسِ بنِ سَمْعَانَ ، قَالَ: سَمِعْتُ رسولَ الله ، يقولُ: ((يُؤْتَى يَوْمَ القِيَامَةِ بِالقُرْآنِ وَأهْلِهِ الذينَ كَانُوا يَعْمَلُونَ بِهِ في الدُّنْيَا تَقْدُمُه سورَةُ البَقَرَةِ وَآلِ عِمْرَانَ، تُحَاجَّانِ عَنْ صَاحِبِهِمَا)) رواه مسلم.",
     "no": "2/107"
    },
    "3": {
     "arab": "وعن عثمان بن عفان ، قَالَ: قَالَ رسول الله : ((خَيْرُكُمْ مَنْ تَعَلَّمَ الْقُرْآنَ وَعَلَّمَهُ)) رواه البخاري.",
     "no": "3/108"
    },
    "4": {
     "arab": "وعن عائشة رضي الله عنها، قالت: قَالَ رسول الله : ((الَّذِي يَقْرَأُ القُرْآنَ وَهُوَ مَاهِرٌ بِهِ مَعَ السَّفَرَةِ الكِرَامِ البَرَرَةِ، وَالَّذِي يَقْرَأُ الْقُرْآنَ وَيَتَتَعْتَعُ فِيهِ وَهُوَ عَلَيْهِ شَاقٌّ لَهُ أجْرَانِ)) متفقٌ عَلَيْهِ.",
     "no": "4/109"
    },
    "5": {
     "arab": "وعن أَبي موسى الأشعري ، قَالَ: قَالَ رسول الله : ((مَثَلُ الْمُؤْمِنِ الَّذِي يَقْرَأُ القُرْآنَ مَثَلُ الأُتْرُجَّةِ: رِيحُهَا طَيِّبٌ وَطَعْمُهَا طَيِّبٌ، وَمَثَلُ الْمُؤْمِنِ الَّذِي لاَ يَقْرَأُ القُرْآنَ كَمَثَلِ التَّمْرَةِ: لاَ رِيحَ لَهَا وَطَعْمُهَا حُلْوٌ، وَمَثلُ المُنَافِقِ الَّذِي يقرأ القرآنَ كَمَثلِ الرَّيحانَةِ: ريحُهَا طَيِّبٌ وَطَعْمُهَا مُرٌّ، وَمَثَلُ المُنَافِقِ الَّذِي لاَ يَقْرَأُ القُرْآنَ كَمَثلِ الحَنْظَلَةِ: لَيْسَ لَهَا رِيحٌ وَطَعْمُهَا مُرٌّ)) متفقٌ عَلَيْهِ.",
     "no": "5/110"
    },
    "6": {
     "arab": "وعن عمر بن الخطاب : أنَّ النبيَّ ، قَالَ: ((إنَّ اللهَ يَرْفَعُ بِهَذَا الكِتَابِ أقْوَاماً وَيَضَعُ بِهِ آخرِينَ)) رواه مسلم.",
     "no": "6/111"
    },
    "7": {
     "arab": "وعن ابن عمر رضي اللهُ عنهما، عن النَّبيِّ ، قَالَ: ((لاَ حَسَدَ إِلاَّ في اثْنَتَيْنِ: رَجُلٌ آتَاهُ اللهُ القُرْآنَ، فَهُوَ يَقُومُ بِهِ آنَاء اللَّيْلِ وَآنَاءَ النَّهَارِ، وَرَجُلٌ آتَاهُ اللهُ مَالاً، فَهُوَ يُنْفِقُهُ آنَاءَ اللَّيْلِ وَآنَاءَ النَّهَارِ)) متفقٌ عَلَيْهِ. ((والآنَاءُ)): السَّاعَاتُ.",
     "no": "7/112"
    },
    "8": {
     "arab": "وعن ابن مسعودٍ ، قَالَ: قَالَ رسولُ اللهِ : ((مَنْ قَرَأ حَرْفاً مِنْ كِتَابِ اللهِ فَلَهُ حَسَنَةٌ، وَالحَسَنَةُ بِعَشْرِ أمْثَالِهَا، لاَ أقول: ألم((4)) حَرفٌ، وَلكِنْ: ألِفٌ حَرْفٌ، وَلاَمٌ حَرْفٌ، وَمِيمٌ حَرْفٌ)) رواه الترمذي، وقال: ((حديث حسن صحيح)).",
     "no": "8/113"
    },
    "9": {
     "arab": "وعن ابن عباسٍ رضي الله عنهما، قَالَ: قَالَ رسول الله : ((إنَّ الَّذِي لَيْسَ في جَوْفِهِ شَيْءٌ مِنَ القُرْآنِ كَالبَيْتِ الخَرِبِ)) رواه الترمذي، وقال: ((حديث حسن صحيح)).",
     "no": "9/114"
    },
    "10": {
     "arab": "وعن عبد اللهِ بن عمرو بن العاص رضي الله عنهما، عن النبيِّ ، قَالَ: ((يُقَالُ لِصَاحِبِ الْقُرْآنِ: اقْرَأْ وَارْتَقِ وَرَتِّلْ كَمَا كُنْتَ تُرَتِّلُ في الدُّنْيَا، فَإنَّ مَنْزِلَتَكَ عِنْدَ آخِرِ آية تَقْرَؤُهَا)) رواه أَبُو داود والترمذي، وقال: ((حديث حسن صحيح)).",
     "no": "10/115"
    }
   }
  },
  "bab-181": {
   "nama": "181- باب الأمر بتعهد القرآن والتحذير عن تعريضه للنسيان",
   "urutan": 181,
   "segmen": {
    "1": {
     "arab": "عن أَبي موسى ، عن النبيِّ ، قَالَ: ((تعاهدوا هَذَا القُرْآنَ، فَوَالَّذِي نَفْسُ مُحَمَّدٍ بِيَدِهِ لَهُوَ أشَدُّ تَفَلُّتاً مِنَ الإبلِ فِي عُقُلِهَا)) متفقٌ عَلَيْهِ.",
     "no": "1/116"
    },
    "2": {
     "arab": "وعن ابن عمر رضي الله عنهما: أنَّ رسول الله ، قَالَ: ((إنَّمَا مَثَلُ صَاحبِ الْقُرْآنِ كَمَثَلِ الإِبِلِ المُعَقَّلَةِ، إنْ عَاهَدَ عَلَيْهَا أمْسَكَهَا، وَإنْ أطْلَقَهَا ذَهَبَتْ)) متفقٌ عَلَيْهِ.",
     "no": "2/117"
    }
   }
  },
  "bab-182": {
   "nama": "182- باب استحباب تحسين الصوت بالقرآن وطلب القراءة من حسن الصوت والاستماع لها",
   "urutan": 182,
   "segmen": {
    "1": {
     "arab": "وعن أَبي هريرة ، قَالَ: سَمِعْتُ رسولَ اللهِ ، يقول: ((مَا أَذِنَ اللهُ لِشَيءٍ مَا أَذِنَ لِنَبِيٍّ حَسَنِ الصَّوْتِ يَتَغَنَّى بِالقُرْآنِ يَجْهَرُ بِهِ)) متفقٌ عَلَيْهِ. مَعْنَى ((أَذِنَ الله)): أي اسْتَمَعَ، وَهُوَ إشَارَةٌ إِلَى الرِّضَا والقَبولِ.",
     "no": "1/118"
    },
    "2": {
     "arab": "وعن البَراءِ بنِ عازِبٍ رضي اللهُ عنهما، قَالَ: سَمِعْتُ النبيَّ  قَرَأَ فِي الْعِشَاءِ بالتِّينِ وَالزَّيْتُونِ، فَمَا سَمِعْتُ أحَداً أحْسَنَ صَوْتاً مِنْهُ. متفقٌ عَلَيْهِ.",
     "no": "2/119"
    },
    "3": {
     "arab": "وعن أَبي لُبَابَةَ بشير بن عبد المنذر : أنَّ النبيَّ ، قَالَ: ((مَنْ لَمْ يَتَغَنَّ بِالقُرْآنِ فَلَيْسَ مِنَّا)) رواه أَبُو داود بإسنادٍ جيدٍ.  معنى ((يَتَغَنَّى)): يُحَسِّنُ صَوْتَهُ بِالقُرْآنِ.",
     "no": "3/120"
    },
    "4": {
     "arab": "وعن ابن مسعودٍ ، قَالَ: قَالَ لِي النَّبيُّ : ((اقْرَأْ عَلَيَّ القُرْآنَ))، فقلتُ: يَا رسولَ الله، أَقْرَأُ عَلَيْكَ، وَعَلَيْكَ أُنْزِلَ ؟! قَالَ: ((إنِّي أُحِبُّ أنْ أسْمَعَهُ مِنْ غَيْرِي)) فَقَرَأْتُ عَلَيْهِ سُورَةَ النِّسَاءِ، حَتَّى جِئْتُ إِلَى هذِهِ الآية:      فَكَيْفَ إِذَا جِئْنَا مِنْ كُلِّ أُمَّةٍ بِشَهِيدٍ وَجِئْنَا بِكَ عَلَى هَؤُلاَءِ شَهِيداً  قَالَ:((حَسْبُكَ الآنَ)) فَالْتَفَتُّ إِلَيْهِ، فَإذَا عَيْنَاهُ تَذْرِفَانِ. متفقٌ عَلَيْهِ.",
     "no": "4/121"
    }
   }
  },
  "bab-183": {
   "nama": "183- باب الحث عَلَى سور وآيات مخصوصة",
   "urutan": 183,
   "segmen": {
    "1": {
     "arab": "عن أَبي سَعِيدٍ رَافِعِ بن الْمُعَلَّى ، قَالَ: قَالَ لي رسولُ اللهِ : ((أَلاَ أُعَلِّمُكَ أَعْظَمَ سُورَةٍ في القُرْآن قَبْلَ أنْ تَخْرُجَ مِنَ الْمَسْجِدِ ؟)) فَأخَذَ بِيَدِي، فَلَمَّا أرَدْنَا أنْ نَخْرُجَ، قُلْتُ: يَا رَسُولَ اللهِ، إنَّكَ قُلْتَ: لأُعَلِّمَنَّكَ أعْظَمَ سُورَةٍ في القُرْآنِ ؟ قَالَ: ((الحَمْدُ للهِ رَبِّ العَالَمِينَ، هِيَ السَّبْعُ المَثَانِي وَالقُرْآنُ العَظِيمُ الَّذِي أُوتِيتُهُ)) رواه البخاري.",
     "no": "1/122"
    },
    "2": {
     "arab": "وعن أَبي سعيد الخدري : أنَّ رسول الله ، قَالَ في:  قُلْ هُوَ اللهُ أَحَدٌ : ((وَالَّذِي نَفْسِي بِيَدِهِ إنَّهَا لَتَعْدِلُ ثُلُثَ القُرْآنِ)). وفي روايةٍ: أن رسول الله ، قَالَ لأَصْحَابِهِ: ((أَيَعْجِزُ أحَدُكُمْ أنْ يَقْرَأَ بِثُلُثِ القُرْآنِ فِي لَيْلَةٍ)) فَشَقَّ ذَلِكَ عَلَيْهِمْ، وَقَالُوا: أيُّنَا يُطِيقُ ذَلِكَ يَا رسولَ الله ؟ فَقَالَ: (( قُلْ هُوَ اللهُ أَحَدٌ اللهُ الصَّمَدُ : ثُلُثُ الْقُرْآنِ)) رواه البخاري.",
     "no": "2/123"
    },
    "3": {
     "arab": "وعن أنس : أنَّ رَجُلاً قَالَ: يَا رَسُولَ اللهِ، إني أُحِبُّ هذِهِ السُّورَةَ:  قُلْ هُوَ اللهُ أحَدٌ  قَالَ: ((إنَّ حُبَّهَا أدْخَلَكَ الجَنَّةَ)) رواه الترمذي، وقال: ((حديث حسن)). ورواه البخاري في صَحِيحِهِ تعليقاً.",
     "no": "3/124"
    },
    "4": {
     "arab": "وعن أَبي سَعِيدٍ الخُدريِّ ، قَالَ: كَانَ رسولُ الله  يَتَعَوَّذُ مِنَ الجَانِّ، وَعَيْنِ الإنْسَانِ، حَتَّى نَزَلَتْ المُعَوِّذَتَانِ، فَلَمَّا نَزَلَتَا، أخَذَ بِهِمَا وَتَرَكَ مَا سِوَاهُمَا. رواه الترمذي، وقال: ((حديث حسن)).",
     "no": "4/125"
    },
    "5": {
     "arab": "وعن أَبي هريرة : أنَّ رسول الله ، قَالَ: ((مِنَ القُرْآنِ سُورَةٌ ثَلاثُونَ آيَةً شَفَعَتْ لِرَجُلٍ حَتَّى غُفِرَ لَهُ، وَهِيَ:  تَبَارَكَ الَّذِي بِيَدِهِ المُلْكُ )) رواه أَبُو داود والترمذي، وقال: ((حديث حسن)). وفي رواية أَبي داود: ((تَشْفَعُ)).",
     "no": "5/126"
    },
    "6": {
     "arab": "وعن أَبي مسعودٍ البَدْرِيِّ ، عن النبي ، قَالَ: ((مَنْ قَرَأَ بِالآيَتَيْنِ مِنْ آخر سُورَةِ البَقَرَةِ في لَيْلَةٍ كَفَتَاهُ)) متفقٌ عَلَيْهِ.  قِيلَ: كَفَتَاهُ الْمَكْرُوهَ تِلْكَ اللَّيْلَةَ، وَقِيلَ: كَفَتَاهُ مِنْ قِيامِ اللَّيْلِ.",
     "no": "6/127"
    },
    "7": {
     "arab": "وعن أَبي هريرة : أنَّ رسول الله ، قَالَ: ((لاَ تَجْعَلُوا بُيُوتَكُمْ مَقَابِرَ، إنَّ الشَّيْطَانَ يَنْفِرُ مِنَ البَيْتِ الَّذِي تُقْرَأُ فِيهِ سُورَةُ البَقرَةِ)) رواه مسلم.",
     "no": "7/128"
    },
    "8": {
     "arab": "وعن أُبَيِّ بنِ كَعبٍ ، قَالَ: قَالَ رسولُ الله : ((يَا أَبَا الْمُنْذِرِ، أَتَدْري أيُّ آيَةٍ مِنْ كِتَابِ الله مَعَكَ أعْظَمُ ؟)) قُلْتُ:  اللهُ لاَ إلَهَ إِلاَّ هُوَ الحَيُّ القَيُّومُ  فَضَرَبَ فِي صَدْرِي، وقال: ((لِيَهْنِكَ العِلْمُ أَبَا الْمُنْذِرِ)) رواه مسلم.",
     "no": "8/129"
    }
   }
  },
  "bab-184": {
   "nama": "184- باب استحباب الاجتماع عَلَى القراءة",
   "urutan": 184,
   "segmen": {
    "1": {
     "arab": "وعن أَبي هريرة ، قَالَ: قَالَ رسول الله : ((وَمَا اجْتَمَعَ قَوْمٌ فِي بَيْتٍ مِنْ بُيُوتِ اللهِ يَتلُونَ كِتَابَ اللهِ، وَيَتَدَارَسُونَهُ بينهم، إِلاَّ نَزَلَتْ عَلَيْهِمُ السَّكِينَةُ وَغَشِيتْهُمُ الرَّحْمَةُ، وَحَفَّتْهُمُ المَلاَئِكَةُ، وَذَكَرَهُمُ اللهُ فِيمَنْ عِنْدَهُ)) رواه مسلم.",
     "no": "1/130"
    }
   }
  }
 }
}